  2           0 LOAD_CONST               1 ('w')
              3 STORE_FAST               1 (key)

  3           6 LOAD_FAST                0 (cipher)
              9 LOAD_ATTR                0 (split)
             12 LOAD_CONST               2 (' ')
             15 CALL_FUNCTION            1
             18 STORE_FAST               2 (a)

  4          21 LOAD_GLOBAL              1 (ord)
             24 LOAD_FAST                1 (key)
             27 CALL_FUNCTION            1
             30 STORE_FAST               3 (key_1)

  5          33 LOAD_GLOBAL              2 (int)
             36 LOAD_FAST                1 (key)
             39 LOAD_ATTR                3 (encode)
             42 LOAD_CONST               3 ('hex')
             45 CALL_FUNCTION            1
             48 CALL_FUNCTION            1
             51 STORE_FAST               4 (key_2)

  6          54 LOAD_FAST                3 (key_1)
             57 LOAD_FAST                4 (key_2)
             60 BUILD_LIST               2
             63 STORE_FAST               5 (keyes)

  7          66 LOAD_CONST               4 ('')
             69 STORE_FAST               0 (cipher)

  8          72 SETUP_LOOP             159 (to 234)
             75 LOAD_GLOBAL              4 (range)
             78 LOAD_CONST               5 (0)
             81 LOAD_GLOBAL              5 (len)
             84 LOAD_FAST                2 (a)
             87 CALL_FUNCTION            1
             90 CALL_FUNCTION            2
             93 GET_ITER            
        >>   94 FOR_ITER               136 (to 233)
             97 STORE_FAST               6 (x)

  9         100 LOAD_FAST                6 (x)
            103 LOAD_CONST               6 (2)
            106 BINARY_MODULO       
            107 LOAD_CONST               7 (1)
            110 COMPARE_OP               2 (==)
            113 POP_JUMP_IF_FALSE      165

 10         116 LOAD_FAST                0 (cipher)
            119 LOAD_GLOBAL              6 (chr)
            122 LOAD_GLOBAL              2 (int)
            125 LOAD_FAST                2 (a)
            128 LOAD_FAST                6 (x)
            131 BINARY_SUBSCR       
            132 CALL_FUNCTION            1
            135 LOAD_CONST               8 (128)
            138 LOAD_FAST                5 (keyes)
            141 LOAD_CONST               5 (0)
            144 BINARY_SUBSCR       
            145 BINARY_SUBTRACT     
            146 LOAD_FAST                5 (keyes)
            149 LOAD_CONST               5 (0)
            152 BINARY_SUBSCR       
            153 BINARY_ADD          
            154 BINARY_XOR          
            155 CALL_FUNCTION            1
            158 INPLACE_ADD         
            159 STORE_FAST               0 (cipher)
            162 JUMP_ABSOLUTE           94

 11     >>  165 LOAD_FAST                6 (x)
            168 LOAD_CONST               6 (2)
            171 BINARY_MODULO       
            172 LOAD_CONST               5 (0)
            175 COMPARE_OP               2 (==)
            178 POP_JUMP_IF_FALSE       94

 12         181 LOAD_FAST                0 (cipher)
            184 LOAD_GLOBAL              6 (chr)
            187 LOAD_GLOBAL              2 (int)
            190 LOAD_FAST                2 (a)
            193 LOAD_FAST                6 (x)
            196 BINARY_SUBSCR       
            197 CALL_FUNCTION            1
            200 LOAD_CONST               8 (128)
            203 LOAD_FAST                5 (keyes)
            206 LOAD_CONST               7 (1)
            209 BINARY_SUBSCR       
            210 BINARY_SUBTRACT     
            211 LOAD_FAST                5 (keyes)
            214 LOAD_CONST               7 (1)
            217 BINARY_SUBSCR       
            218 BINARY_ADD          
            219 BINARY_XOR          
            220 CALL_FUNCTION            1
            223 INPLACE_ADD         
            224 STORE_FAST               0 (cipher)
            227 JUMP_ABSOLUTE           94
            230 JUMP_ABSOLUTE           94
        >>  233 POP_BLOCK           

 13     >>  234 LOAD_FAST                0 (cipher)
            237 PRINT_ITEM          
            238 PRINT_NEWLINE       
            239 LOAD_CONST               0 (None)
            242 RETURN_VALUE        